{
  "person_id": "malaysia_male_19880110_P005",
  "name": "1988年马来西亚出生男性",
  "birth_input": {
    "year": 1988,
    "month": 1,
    "day": 10,
    "hour": 8,
    "minute": 12,
    "place": "马来西亚",
    "raw": "1988-01-10T08:12 - 马来西亚（西历：1988年1月10日 早上8时12分 马来西亚出生）",
    "approximate": false
  },
  "generator": "/home/sunnysab/Code/0-Cloned/bazi/bazi.py",
  "generated_at": "2026-03-28T14:15:26.022265+00:00",
  "raw_output": "------------------------------------------------------------------------------------------------------------------------\n男命 \t公历: 1988年1月10日   农历: 1987年11月21日 穿=害 上运时间：1989-04-20 命宫:壬子 胎元:甲辰 身宫:丙午\n \t 小寒后癸水9日，辛金3日，己土18日。小寒、大寒。 小寒 1988-01-06 11:03:30 大寒 1988-01-21 04:24:17\n------------------------------------------------------------------------------------------------------------------------\n\u001b[1;36;40m丁 癸 甲 戊       伤 印 -- 才\u001b[0m      金:相 木:囚 水:死 火:休 土:旺  金2  木15  水18  火5  土20  强弱:33 中值29 强根: 有\n\u001b[1;36;40m卯 丑 子 辰       劫 财 印 才\u001b[0m     -11 湿度[-6,6] 拱：[] 解读:钉ding或v信pythontesting: 四柱：丁卯 癸丑 甲子 戊辰\n------------------------------------------------------------------------------------------------------------------------\n　　　　【年】4:1午　　　　　　　【月】-6:-4子　　　　　　　【日】3:-6　　　　　　　【时】5:-4巳|　　　\n------------------------------------------------------------------------------------------------------------------------\n\u001b[1;36;40m丁－火【伤】冲癸　　　　　　　癸－水【印】合戊冲丁　　　　　甲＋木　　　　　　　　　　　　戊＋土【才】合癸　　　　　　　\u001b[0m\n\u001b[1;36;40m卯－病长【帝】沐　　　　　　　丑－墓冠【冠】养　　　　　　　子＋绝建【沐】胎　　　　　　　辰＋衰养【衰】冠　　　　　　　\u001b[0m\n\u001b[1;36;40m乙木劫　　　　　　　　　　　　\u001b[0m\u001b[1;36;40m己土财　癸水印　辛金官　　　　\u001b[0m\u001b[1;36;40m癸水印　　　　　　　　　　　　\u001b[0m\u001b[1;36;40m戊土才　乙木劫　癸水印　　　　\u001b[0m\n\u001b[1;36;40m被刑：子　　　　　　　　　　　\u001b[0m\u001b[1;36;40m六：子　　　　　　　　　　　　\u001b[0m\u001b[1;36;40m被刑：卯　合：辰　六：丑　　　\u001b[0m\u001b[1;36;40m合：子　　　　　　　　　　　　\u001b[0m\n\u001b[1;36;40m刑：子　会：辰　害：辰　　　　\u001b[0m\u001b[1;36;40m会：子　破：辰　　　　　　　　\u001b[0m\u001b[1;36;40m刑：卯　会：丑　　　　　　　　\u001b[0m\u001b[1;36;40m会：卯　害：卯　破：丑　　　　\u001b[0m\n\u001b[1;36;40m无根　　　　　　　　　　　　　\u001b[0m\u001b[1;36;40m强：子　中：丑　弱：辰　　　　\u001b[0m\u001b[1;36;40m强：卯　中：辰　　　　　　　　\u001b[0m\u001b[1;36;40m强：丑辰　　　　　　　　　　　\u001b[0m\n↑炉中火　　　　　　　　　　　 ←桑柘木　　　　　　　　　　　 ↑海中金　　　　　　　　　　　 =大林木　　　　　　　　　　　 \n阳刃　　　　　　　　　　　　　 寡宿　天乙　　　　　　　　　　 　　　　　　　　　　　　　　 华盖　　　　　　　　　　　　 \n------------------------------------------------------------------------------------------------------------------------\n胆: 2  肝: 1  小肠: 0  心: 1  胃: 2  脾: 0  大肠: 1  肺: 0  膀胱: 0  肾: 1  三焦: 0  心包: 0  \n------------------------------------------------------------------------------------------------------------------------\n大运： 壬子 辛亥 庚戌 己酉 戊申 丁未 丙午 乙巳 甲辰 癸卯 壬寅 辛丑 \n2        壬子 沐 桑柘木    枭:壬＋合丁　　　　　子＋沐 - 癸印　　　　　　　　 会:丑  刑:卯  六:丑  被刑:卯  合:辰  神:将星\n12       辛亥 长 钗钏金    官:辛－　　　　　　空亥－长 - 壬枭　甲比　　　　　 会:子  会:丑  合:卯  神:亡神\n22       庚戌 养 钗钏金    杀:庚＋冲甲　　　　空戌＋养 - 戊才　辛官　丁伤　　 六:卯  被刑:丑  冲:辰  神:大耗 天德 月德\n32       己酉 胎 大驿土    财:己－合甲　　　　　酉－胎 - 辛官　　　　　　　　 合:丑  冲:卯  六:辰  破:子  神:桃花\n42       戊申 绝 大驿土    才:戊＋合癸　　　　　申＋绝 - 庚杀　壬枭　戊才　　 合:辰  暗:卯  合:子  神:大耗\n52       丁未 墓 天河水    伤:丁－冲癸　　　　　未－墓 - 己财　丁伤　乙劫　　 刑:丑  冲:丑  合:卯  害:子  神:天乙\n62       丙午 死 天河水    食:丙＋　　　　　　　午＋死 - 丁伤　己财　　　　　 害:丑  破:卯  冲:子  神:红艳\n72       乙巳 病 覆灯火    劫:乙－　　　　　　　巳－病 - 丙食　戊才　庚杀　　 合:丑  神:孤辰 劫煞 文昌\n82       甲辰 衰 覆灯火    比:甲＋　　　　　　　辰＋衰 - 戊才　乙劫　癸印　　 会:卯  破:丑  被刑:辰  合:子  刑:辰  害:卯  神:华盖\n------------------------------------------------------------------------------------------------------------------------\n调候： 1丁2丙庚 \t##金不换大运： 调候：喜丁 忌壬辛癸  大运：喜寅卯申酉 忌午未\n金不换大运：说明： 辰戌丑未入墓库运；巳未申酉亥月有夭折运；申酉戌亥月调候待改进！\n格局选用： 食伤生财：最佳      财格：        印格；体弱多病 杀印相生：    官杀：六亲稀少 伤官配印：\n缺四生：一生不敢作为\n月日时支没有财或偏财的禄旺。\n月日时支没有官的禄旺。\n阳刃 : 性格刚强，女命未必佳。\n华盖 : 有艺术、水准与命格相关。\n天乙 : 后天解难、女命不适合多\n寡宿 : 类似孤辰，同柱有天月德没关系。男怕孤，女怕寡。\n------------------------------------------------------------------------------------------------------------------------\n甲:比 兄弟-帝 冠 沐 衰  乙:劫 姐妹-建 衰 病 冠  丙:食 下属-沐 养 胎 冠  丁:伤 孙女-病 墓 绝 衰  戊:才 父亲-沐 养 胎 冠  \n己:财 妻-病 墓 绝 衰  庚:杀 儿子-胎 墓 死 养  辛:官 女儿-绝 养 长 墓  壬:枭 祖父-死 衰 帝 墓  癸:印 母亲-长 冠 建 养  \n\n甲[比]-5   乙[劫]-10   丙[食]-0   丁[伤]-5   戊[才]-10   己[财]-10   庚[杀]-0   辛[官]-2   壬[枭]-0   癸[印]-18   \n------------------------------------------------------------------------------------------------------------------------\n子 天贵星、志气不凡、富裕清吉。\n坐： 虽坐沐浴，若四往有禄，看印，冬生不作妻败\n甲子：调候要火。\n同一柱中，劫财、阳刃伤官都有，外表华美，富屋穷人，婚姻不稳定，富而不久；年柱不利家长，月柱不利婚姻，时柱不利子女。伤官的狂妄。基55丙申 丁酉 甲子 丁卯\n年阳刃：得不到长辈福；不知足、施恩反怨。\n基础82，成格喜官杀、身弱、忌财克印。合印留财，见利忘义.透财官杀通关或印生比劫；合冲印若无他格或调候破格。日主强凶，禄刃一支可以食伤泄。\n印月重叠：女迟婚，月阳刃者离寡，能独立谋生，有修养的才女。\n正印多的：聪明有谋略，比较含蓄，不害人，识时务。正印不怕日主死绝，反而怕太强。日主强，正印多，孤寂，不善理财。 pd41男的克妻，子嗣少。女的克母。\n男正印坐正财，夫妻不好。月柱正印坐正财专位，必离婚。在时柱，50多岁才有正常婚姻。(男) 基59 乙酉 己卯 庚子 丁亥  庚申 庚辰 庚午 己卯\n单独正印主秀气、艺术、文才。性格保守\n正印怕财。\n坐印，时偏财格：他乡发迹，改弦易宗，妻贤子孝。 母法总则：P55-1 丁丑 丁未 甲子 戊辰\n偏财明现天干，不论是否有根:财富外人可见;实际财力不及外观一半。没钱别人都不相信;协助他人常超过自己的能力\n偏财出天干，又与天月德贵人同一天干者。在年月有声明远扬的父亲，月时有聪慧的红颜知己。喜奉承。\n偏财透天干，四柱没有刑冲，长寿。女子为孝顺女，主要针对年月。时柱表示中年以后有自己的事业，善于理财。\n财格基础80:比劫用食伤通关或官杀制；身弱有比劫仍然用食伤通关。如果时柱坐实比劫，晚年破产。\n偏财透天干，讲究原则，不拘小节。喜奉承，善于享受。财格基础80\n偏财坐阳刃劫财,可做父缘薄，也可幼年家贫。也可以父先亡，要参考第一大运。偏财坐专位阳刃劫财,父亲去他乡.基61壬午 壬寅 戊子 丁巳\n月令正财，无冲刑，有贤内助，但是母亲与妻子不和。生活简朴，多为理财人士。\n伤官有才华，但是清高。要生财，或者印制。\n伤官配印，无财，有手艺，但是不善于理财。有一定个性\n伤官地支坐阳刃，力不从心 基70己酉 丁卯 甲午 辛未。背禄逐马，克官劫财。影响15年。伤官坐劫财：只适合纯粹之精明商人或严谨掌握财之人。\n局 [] 格 ['印', '才']\n\n\n《六十日用法口诀》\n=========================\n天德贵人日。坐子、沐浴，逢官临桃花。\n白玉仙子捧印来，一举成名天门开。\n贵人不向西方去，烽火空负旷世才。\n辛为正官，庚为偏官，戊己为财，见甲乙为破财，丙丁伤名利艰难，生在子月，无丑合，离祖自立，亥卯辰月主贵，巳月平常之命，午月甲死子神冲，他乡立业。申月，子嗣难有。辰月，移根换叶。亥月，文章显达。\n\n\n《穷通宝鉴》\n=========================\n\n    十二月甲木，天寒气冻，木性极寒，无生发之象，先用庚劈甲，方引丁火始得木火有通明之象，故丁次之。\n    庚丁两透，科甲恩封。庚透丁藏，小贵。丁透庚藏，小富贵。无庚者，贫贱。无丁者，寒儒。或有丁透重重，亦是富贵中人，但须比肩，能发丁之焰，自有德业才能。如无比肩，寻常之士，稍有衣食而已。或支多见水，即有比肩，亦属平常。\n    总之腊月甲木，虽有庚金，丁不可少。乏庚略可，乏丁无用。经云：甲木无根，男女夭寿  \n    \n\n\n《三命通会》\n=========================\n\n    六甲日生时戊辰,天财坐库会滋身; 富商巨贾田园盛,月带辛金名利成。 \n    甲日戊辰时,天财坐库,时上偏财,遇龙守库,主为商贾发财,田园广盛。八月带禄,财官俱有,富贵双全。忌比肩、羊刃夺财。\n    # 偏财坐印，生于夏季、有辰调候，佳命。\n    # 1-155 印库，50以后得权。\n\n    时上偏财不用多,干枝内外细搜罗; 运通财旺官生至,运拙身衰恐受磨。 \n    甲日戊辰时遇,柱中要戌相扶。财官运气展良图,喜遇钱龙守库。 \n    辛庚透干贵显,壬癸滋助不枯。只怕比劫弟兄多,岁运逢之有祸。\n\n    甲子日戊辰时,主移根换叶,改姓易宗,妻贤子孝,作高 命论。未月,行北方运,贵。酉月,北方运,大贵。 \n\n    甲寅日戊辰时,龙吟虎啸格,贵。纯辰,中贵。纯寅康寿。 亥卯未三合,财旺身强,大贵。酉丑申年月亦吉。 \n\n    甲辰日戊辰时,刑冲发财,妻重子晚,双亲有克。酉月三四品贵。丑月亦贵。地支纯辰,大贵。\n\n    甲午日戊辰时,财多成败,早岁灰心。亥子丑卯午未年月大贵。酉月亦贵。\n\n    甲申日戊辰时,主孤,僧道清高。丑月富贵。寅月尤贵。 \n    甲戌日戊辰时,大富,年月扶合亦贵。寅亥年月,三四品贵。但时日并冲克,早年身孤,中年发福。\n    \n\n\n《十二时辰（初中末）出生吉凶》\n=========================\n辰时初\n衣禄自然来，兄弟六亲林，父母难刑克，晚景更无忧。\n辰时初父母在，为人性急，六亲有力，长子难招，兄弟不和，心慈善，宜手艺营生，初限平平，四十二岁后渐好。\n\n辰时中\n衣禄得人抬，先忧后吉来，六亲虽冷淡，末限足钱财。\n辰时中先克父，为人心行公道，性急直燥，出入有贵人扶持，离祖成家，六亲兄弟情疏，初年不济，末限胜前。\n\n辰时末\n衣禄自然有，朱紫作朝郎，一朝命发达，富贵有名声。\n辰时末先克母，为人聪明，衣禄丰盈，大有声名，六亲大旺，兄分有顾盼，为官头目之称，女命益夫，旺子福禄双全。\n\n\n大运\n========================================================================================================================\n2        壬子 沐 桑柘木    枭:壬＋合丁　　　　　子＋沐 - 癸印　　　　　　　　 会:丑  刑:卯  六:丑  被刑:卯  合:辰  神:将星\n  2 1989 己巳 病 大林木    财:己－合甲　　　　　巳－病 - 丙食　戊才　庚杀　　 合:丑  神:孤辰 劫煞 文昌\n  3 1990 庚午 死 路旁土    杀:庚＋冲甲　　　　　午＋死 - 丁伤　己财　　　　　 害:丑  冲:子  神:天德 月德 红艳\n  4 1991 辛未 墓 路旁土    官:辛－　　　　　　　未－墓 - 己财　丁伤　乙劫　　 刑:丑  冲:丑  合:卯  害:子  神:天乙\n  5 1992 壬申 绝 剑锋金    枭:壬＋合丁　　　　　申＋绝 - 庚杀　壬枭　戊才　　 合:辰  暗:卯  合:子  神:大耗\n  6 1993 癸酉 胎 剑锋金    印:癸－合戊冲丁　　　酉－胎 - 辛官　　　　　　　　 合:丑  冲:卯  六:辰  神:桃花\n  7 1994 甲戌 养 山头火    比:甲＋　　　　　　空戌＋养 - 戊才　辛官　丁伤　　 六:卯  被刑:丑  冲:辰  --夹：戌  神:大耗\n  8 1995 乙亥 长 山头火    劫:乙－　　　　　　空亥－长 - 壬枭　甲比　　　　　 会:子  会:丑  合:卯  神:亡神\n  9 1996 丙子 沐 涧下水    食:丙＋冲壬　　　　　子＋沐 - 癸印　　　　　　　　 会:丑  刑:卯  六:丑  被刑:卯  合:辰  神:将星\n 10 1997 丁丑 冠 涧下水    伤:丁－合壬冲癸　　　丑－冠 - 己财　癸印　辛官　　 会:子  六:子  --夹：寅  神:寡宿 天乙\n 11 1998 戊寅 建 城头土    才:戊＋合癸　　　　　寅＋建 - 甲比　丙食　戊才　　 会:卯  会:辰  暗:丑  --夹：卯  神:驿马\n12       辛亥 长 钗钏金    官:辛－　　　　　　空亥－长 - 壬枭　甲比　　　　　 会:子  会:丑  合:卯  神:亡神\n 12 1999 己卯 帝 城头土    财:己－合甲　　　　　卯－帝 - 乙劫　　　　　　　　 合:亥  害:辰  被刑:子  刑:子  会:辰  神:阳刃\n 13 2000 庚辰 衰 白蜡金    杀:庚＋冲甲　　　　　辰＋衰 - 戊才　乙劫　癸印　　 会:卯  被刑:辰  合:子  刑:辰  害:卯  神:天德 月德 华盖\n 14 2001 辛巳 病 白蜡金    官:辛－　　　　　　　巳－病 - 丙食　戊才　庚杀　　 冲:亥  合:丑  神:孤辰 劫煞 文昌\n 15 2002 壬午 死 杨柳木    枭:壬＋合丁　　　　　午＋死 - 丁伤　己财　　　　　 害:丑  暗:亥  冲:子  神:红艳\n 16 2003 癸未 墓 杨柳木    印:癸－合戊冲丁　　　未－墓 - 己财　丁伤　乙劫　　 刑:丑  合:卯  害:子  合:亥  冲:丑  神:天乙\n 17 2004 甲申 绝 井泉水    比:甲＋　　　　　　　申＋绝 - 庚杀　壬枭　戊才　　 害:亥  合:辰  暗:卯  合:子  神:大耗\n 18 2005 乙酉 胎 井泉水    劫:乙－冲辛　　　　　酉－胎 - 辛官　　　　　　　　 合:丑  冲:卯  六:辰  神:桃花\n 19 2006 丙戌 养 屋上土    食:丙＋合辛　　　　空戌＋养 - 戊才　辛官　丁伤　　 六:卯  被刑:丑  冲:辰  神:大耗\n 20 2007 丁亥 长 屋上土    伤:丁－冲癸　　　　空亥－长 - 壬枭　甲比　　　　　 会:子  会:丑  刑:亥  合:卯  被刑:亥  神:亡神\n 21 2008 戊子 沐 霹雳火    才:戊＋合癸　　　　　子＋沐 - 癸印　　　　　　　　 会:丑  会:亥  刑:卯  六:丑  被刑:卯  合:辰  神:将星\n22       庚戌 养 钗钏金    杀:庚＋冲甲　　　　空戌＋养 - 戊才　辛官　丁伤　　 六:卯  被刑:丑  冲:辰  神:大耗 天德 月德\n 22 2009 己丑 冠 霹雳火    财:己－合甲　　　　　丑－冠 - 己财　癸印　辛官　　 会:子  刑:戌  六:子  神:寡宿 天乙\n 23 2010 庚寅 建 松柏木    杀:庚＋冲甲　　　　　寅＋建 - 甲比　丙食　戊才　　 会:卯  合:戌  会:辰  暗:丑  --拱：午  神:天德 月德 驿马\n 24 2011 辛卯 帝 松柏木    官:辛－　　　　　　　卯－帝 - 乙劫　　　　　　　　 六:戌  害:辰  被刑:子  刑:子  会:辰  神:阳刃\n 25 2012 壬辰 衰 长流水    枭:壬＋合丁　　　　　辰＋衰 - 戊才　乙劫　癸印　　 会:卯  冲:戌  被刑:辰  合:子  刑:辰  害:卯  神:华盖\n 26 2013 癸巳 病 长流水    印:癸－合戊冲丁　　　巳－病 - 丙食　戊才　庚杀　　 合:丑  --拱：酉  神:孤辰 劫煞 文昌\n 27 2014 甲午 死 砂中金    比:甲＋冲庚　　　　　午＋死 - 丁伤　己财　　　　　 合:戌  害:丑  冲:子  神:红艳\n 28 2015 乙未 墓 砂中金    劫:乙－合庚　　　　　未－墓 - 己财　丁伤　乙劫　　 刑:丑  合:卯  害:子  冲:丑  被刑:戌  神:天乙  四库：辰戌丑未\n 29 2016 丙申 绝 山下火    食:丙＋　　　　　　　申＋绝 - 庚杀　壬枭　戊才　　 会:戌  合:辰  暗:卯  合:子  神:大耗\n 30 2017 丁酉 胎 山下火    伤:丁－冲癸　　　　　酉－胎 - 辛官　　　　　　　　 六:辰  冲:卯  合:丑  害:戌  会:戌  神:桃花\n 31 2018 戊戌 养 平地木    才:戊＋合癸　　　　空戌＋养 - 戊才　辛官　丁伤　　 六:卯  被刑:丑  冲:辰  神:大耗\n32       己酉 胎 大驿土    财:己－合甲　　　　　酉－胎 - 辛官　　　　　　　　 合:丑  冲:卯  六:辰  破:子  神:桃花\n 32 2019 己亥 长 平地木    财:己－合甲　　　　空亥－长 - 壬枭　甲比　　　　　 会:子  会:丑  合:卯  --夹：戌  神:亡神\n 33 2020 庚子 沐 壁上土    杀:庚＋冲甲　　　　　子＋沐 - 癸印　　　　　　　　 会:丑  刑:卯  六:丑  被刑:卯  合:辰  神:天德 月德 将星\n 34 2021 辛丑 冠 壁上土    官:辛－　　　　　　　丑－冠 - 己财　癸印　辛官　　 会:子  六:子  合:酉  神:寡宿 天乙\n 35 2022 壬寅 建 金泊金    枭:壬＋合丁　　　　　寅＋建 - 甲比　丙食　戊才　　 会:卯  会:辰  暗:丑  神:驿马\n 36 2023 癸卯 帝 金泊金    印:癸－合戊冲丁　　　卯－帝 - 乙劫　　　　　　　　 冲:酉  害:辰  被刑:子  刑:子  会:辰  --夹：寅  神:阳刃\n 37 2024 甲辰 衰 覆灯火    比:甲＋合己　　　　　辰＋衰 - 戊才　乙劫　癸印　　 会:卯  六:酉  被刑:辰  合:子  刑:辰  害:卯  神:华盖\n 38 2025 乙巳 病 覆灯火    劫:乙－　　　　　　　巳－病 - 丙食　戊才　庚杀　　 合:酉  合:丑  神:孤辰 劫煞 文昌\n 39 2026 丙午 死 天河水    食:丙＋　　　　　　　午＋死 - 丁伤　己财　　　　　 害:丑  冲:子  神:红艳  四败：子午卯酉\n 40 2027 丁未 墓 天河水    伤:丁－冲癸　　　　　未－墓 - 己财　丁伤　乙劫　　 刑:丑  冲:丑  合:卯  害:子  神:天乙\n 41 2028 戊申 绝 大驿土    才:戊＋合癸　　　　　申＋绝 - 庚杀　壬枭　戊才　　 会:酉  合:辰  暗:卯  合:子  神:大耗\n42       戊申 绝 大驿土    才:戊＋合癸　　　　　申＋绝 - 庚杀　壬枭　戊才　　 合:辰  暗:卯  合:子  神:大耗\n 42 2029 己酉 胎 大驿土    财:己－合甲　　　　　酉－胎 - 辛官　　　　　　　　 合:丑  冲:卯  六:辰  会:申  神:桃花\n 43 2030 庚戌 养 钗钏金    杀:庚＋冲甲　　　　空戌＋养 - 戊才　辛官　丁伤　　 六:卯  被刑:丑  冲:辰  会:申  神:大耗 天德 月德\n 44 2031 辛亥 长 钗钏金    官:辛－　　　　　　空亥－长 - 壬枭　甲比　　　　　 会:子  会:丑  合:卯  害:申  神:亡神\n 45 2032 壬子 沐 桑柘木    枭:壬＋合丁　　　　　子＋沐 - 癸印　　　　　　　　 会:丑  刑:卯  六:丑  被刑:卯  合:辰  合:申  神:将星\n 46 2033 癸丑 冠 桑柘木 *  印:癸－合戊冲丁　　　丑－冠 - 己财　癸印　辛官　　 会:子  六:子  神:寡宿 天乙\n 47 2034 甲寅 建 大溪水    比:甲＋　　　　　　　寅＋建 - 甲比　丙食　戊才　　 会:卯  被刑:申  冲:申  暗:丑  会:辰  --夹：丑  神:驿马\n 48 2035 乙卯 帝 大溪水    劫:乙－　　　　　　　卯－帝 - 乙劫　　　　　　　　 害:辰  被刑:子  刑:子  会:辰  暗:申  神:阳刃\n 49 2036 丙辰 衰 砂中土    食:丙＋　　　　　　　辰＋衰 - 戊才　乙劫　癸印　　 会:卯  被刑:辰  合:子  刑:辰  合:申  害:卯  神:华盖\n 50 2037 丁巳 病 砂中土    伤:丁－冲癸　　　　　巳－病 - 丙食　戊才　庚杀　　 合:丑  刑:申  六:申  --夹：辰  神:孤辰 劫煞 文昌\n 51 2038 戊午 死 天上火    才:戊＋合癸　　　　　午＋死 - 丁伤　己财　　　　　 害:丑  冲:子  --夹：巳  --夹：未  神:红艳\n52       丁未 墓 天河水    伤:丁－冲癸　　　　　未－墓 - 己财　丁伤　乙劫　　 刑:丑  冲:丑  合:卯  害:子  神:天乙\n 52 2039 己未 墓 天上火    财:己－合甲　　　　　未－墓 - 己财　丁伤　乙劫　　 刑:丑  冲:丑  合:卯  害:子  神:天乙\n 53 2040 庚申 绝 石榴木    杀:庚＋冲甲　　　　　申＋绝 - 庚杀　壬枭　戊才　　 合:辰  暗:卯  合:子  神:大耗 天德 月德\n 54 2041 辛酉 胎 石榴木    官:辛－　　　　　　　酉－胎 - 辛官　　　　　　　　 合:丑  冲:卯  六:辰  神:桃花\n 55 2042 壬戌 养 大海水    枭:壬＋合丁　　　　空戌＋养 - 戊才　辛官　丁伤　　 六:卯  被刑:丑  刑:未  冲:辰  神:大耗  四库：辰戌丑未\n 56 2043 癸亥 长 大海水    印:癸－合戊冲丁　　空亥－长 - 壬枭　甲比　　　　　 会:子  合:未  会:丑  合:卯  --夹：子  神:亡神\n 57 2044 甲子 沐 海中金 *  比:甲＋　　　　　　　子＋沐 - 癸印　　　　　　　　 会:丑  害:未  刑:卯  六:丑  被刑:卯  合:辰  神:将星\n 58 2045 乙丑 冠 海中金    劫:乙－　　　　　　　丑－冠 - 己财　癸印　辛官　　 会:子  六:子  被刑:未  冲:未  神:寡宿 天乙\n 59 2046 丙寅 建 炉中火    食:丙＋　　　　　　　寅＋建 - 甲比　丙食　戊才　　 会:卯  会:辰  暗:丑  神:驿马\n 60 2047 丁卯 帝 炉中火 *  伤:丁－冲癸　　　　　卯－帝 - 乙劫　　　　　　　　 害:辰  合:未  被刑:子  刑:子  会:辰  神:阳刃\n 61 2048 戊辰 衰 大林木 *  才:戊＋合癸　　　　　辰＋衰 - 戊才　乙劫　癸印　　 会:卯  被刑:辰  合:子  刑:辰  害:卯  神:华盖\n62       丙午 死 天河水    食:丙＋　　　　　　　午＋死 - 丁伤　己财　　　　　 害:丑  破:卯  冲:子  神:红艳\n 62 2049 己巳 病 大林木    财:己－合甲　　　　　巳－病 - 丙食　戊才　庚杀　　 合:丑  会:午  神:孤辰 劫煞 文昌\n 63 2050 庚午 死 路旁土    杀:庚＋冲甲　　　　　午＋死 - 丁伤　己财　　　　　 被刑:午  害:丑  刑:午  冲:子  神:天德 月德 红艳\n 64 2051 辛未 墓 路旁土    官:辛－合丙　　　　　未－墓 - 己财　丁伤　乙劫　　 刑:丑  合:卯  害:子  冲:丑  六:午  会:午  神:天乙\n 65 2052 壬申 绝 剑锋金    枭:壬＋合丁冲丙　　　申＋绝 - 庚杀　壬枭　戊才　　 合:辰  暗:卯  合:子  神:大耗\n 66 2053 癸酉 胎 剑锋金    印:癸－合戊冲丁　　　酉－胎 - 辛官　　　　　　　　 合:丑  冲:卯  六:辰  神:桃花  四败：子午卯酉\n 67 2054 甲戌 养 山头火    比:甲＋　　　　　　空戌＋养 - 戊才　辛官　丁伤　　 六:卯  被刑:丑  冲:辰  合:午  --夹：戌  神:大耗\n 68 2055 乙亥 长 山头火    劫:乙－　　　　　　空亥－长 - 壬枭　甲比　　　　　 会:子  会:丑  合:卯  暗:午  神:亡神\n 69 2056 丙子 沐 涧下水    食:丙＋　　　　　　　子＋沐 - 癸印　　　　　　　　 会:丑  刑:卯  六:丑  被刑:卯  合:辰  冲:午  神:将星\n 70 2057 丁丑 冠 涧下水    伤:丁－冲癸　　　　　丑－冠 - 己财　癸印　辛官　　 会:子  六:子  害:午  --夹：寅  神:寡宿 天乙\n 71 2058 戊寅 建 城头土    才:戊＋合癸　　　　　寅＋建 - 甲比　丙食　戊才　　 会:卯  合:午  会:辰  暗:丑  --夹：卯  神:驿马\n72       乙巳 病 覆灯火    劫:乙－　　　　　　　巳－病 - 丙食　戊才　庚杀　　 合:丑  神:孤辰 劫煞 文昌\n 72 2059 己卯 帝 城头土    财:己－合甲　　　　　卯－帝 - 乙劫　　　　　　　　 被刑:子  刑:子  会:辰  害:辰  神:阳刃\n 73 2060 庚辰 衰 白蜡金    杀:庚＋合乙冲甲　　　辰＋衰 - 戊才　乙劫　癸印　　 会:卯  被刑:辰  合:子  刑:辰  害:卯  神:天德 月德 华盖\n 74 2061 辛巳 病 白蜡金    官:辛－冲乙　　　　　巳－病 - 丙食　戊才　庚杀　　 合:丑  神:孤辰 劫煞 文昌\n 75 2062 壬午 死 杨柳木    枭:壬＋合丁　　　　　午＋死 - 丁伤　己财　　　　　 害:丑  会:巳  冲:子  神:红艳\n 76 2063 癸未 墓 杨柳木    印:癸－合戊冲丁　　　未－墓 - 己财　丁伤　乙劫　　 会:巳  刑:丑  合:卯  害:子  冲:丑  神:天乙\n 77 2064 甲申 绝 井泉水    比:甲＋　　　　　　　申＋绝 - 庚杀　壬枭　戊才　　 暗:卯  六:巳  合:辰  合:子  被刑:巳  神:大耗\n 78 2065 乙酉 胎 井泉水    劫:乙－　　　　　　　酉－胎 - 辛官　　　　　　　　 合:巳  合:丑  冲:卯  六:辰  神:桃花\n 79 2066 丙戌 养 屋上土    食:丙＋　　　　　　空戌＋养 - 戊才　辛官　丁伤　　 六:卯  被刑:丑  冲:辰  神:大耗\n 80 2067 丁亥 长 屋上土    伤:丁－冲癸　　　　空亥－长 - 壬枭　甲比　　　　　 会:子  会:丑  冲:巳  合:卯  神:亡神\n 81 2068 戊子 沐 霹雳火    才:戊＋合癸　　　　　子＋沐 - 癸印　　　　　　　　 会:丑  刑:卯  六:丑  被刑:卯  合:辰  神:将星\n82       甲辰 衰 覆灯火    比:甲＋　　　　　　　辰＋衰 - 戊才　乙劫　癸印　　 会:卯  破:丑  被刑:辰  合:子  刑:辰  害:卯  神:华盖\n 82 2069 己丑 冠 霹雳火    财:己－合甲　　　　　丑－冠 - 己财　癸印　辛官　　 会:子  六:子  神:寡宿 天乙\n 83 2070 庚寅 建 松柏木    杀:庚＋冲甲　　　　　寅＋建 - 甲比　丙食　戊才　　 会:卯  会:辰  暗:丑  神:天德 月德 驿马\n 84 2071 辛卯 帝 松柏木    官:辛－　　　　　　　卯－帝 - 乙劫　　　　　　　　 被刑:子  刑:子  会:辰  害:辰  神:阳刃\n 85 2072 壬辰 衰 长流水    枭:壬＋合丁　　　　　辰＋衰 - 戊才　乙劫　癸印　　 会:卯  被刑:辰  合:子  刑:辰  害:卯  神:华盖\n 86 2073 癸巳 病 长流水    印:癸－合戊冲丁　　　巳－病 - 丙食　戊才　庚杀　　 合:丑  --拱：酉  神:孤辰 劫煞 文昌\n 87 2074 甲午 死 砂中金    比:甲＋　　　　　　　午＋死 - 丁伤　己财　　　　　 害:丑  冲:子  --夹：巳  神:红艳\n 88 2075 乙未 墓 砂中金    劫:乙－　　　　　　　未－墓 - 己财　丁伤　乙劫　　 刑:丑  冲:丑  合:卯  害:子  神:天乙\n 89 2076 丙申 绝 山下火    食:丙＋　　　　　　　申＋绝 - 庚杀　壬枭　戊才　　 合:辰  暗:卯  合:子  神:大耗\n 90 2077 丁酉 胎 山下火    伤:丁－冲癸　　　　　酉－胎 - 辛官　　　　　　　　 合:丑  冲:卯  六:辰  神:桃花\n 91 2078 戊戌 养 平地木    才:戊＋合癸　　　　空戌＋养 - 戊才　辛官　丁伤　　 六:卯  被刑:丑  冲:辰  神:大耗\n星宿 虚 虚星造作主灾殃，男女孤眠不一双，内乱风声无礼节，儿孙媳妇伴人床，开门放水遭灾祸，虎咬蛇伤又卒亡，三三五五连年病，家破人亡不可当。\n('闭', '闭藏的日子 宜：安门、伐木、修造、动土。 忌：出行、嫁娶。')\n========================================================================================================================\n| 玉堂贵人： 丑 \n\n------------------------------------------------------------------------------------------------------------------------\n出身: 一般\n财少身强，柱有比劫，不为福\n\n印分析 **** 喜:食神 天月德 七煞 逢印看煞 以官为引   忌： 刑冲 伤官 死墓 辰戊印怕木 丑未印不怕木\n一曰正印 二曰魁星 三曰孙极星\n以印绶多者为上,月最要,日时次之,年干虽重,须归禄月、日、时,方可取用,若年露印,月日时无,亦不济事。\n======================================\n伤食：身强印旺，恐其太过，泄身以为秀气；若印浅身轻，而用层层伤食，则寒贫之局矣。\n有印多而用财者，印重身强，透财以抑太过，权而用之，只要根深，无防财破。 若印轻财重，又无劫财以救，则为贪财破印，贫贱之局也。\n印绶复遇拱禄、专禄、归禄、鼠贵、夹贵、时贵等格,尤为奇特,但主少子或无子,印绶多者清孤。\n化印为劫；弃之以就财官\n\n------------------------------------------------------------------------------------------------------------------------\n========================================================================================================================\n你属: 甲 特点：-- 雷龙 梁栋 禄寅;斧斤斫削成其器。木不南奔;喜春运不喜西方,春生,处世安然,必寿。 \n\n年份: 卯 特点：-- 琼林 乙木 正东 仲春 卯年遇巳未时者，是为兔入月宫之象，主大贵。 \n\n\n羊刃: 甲 卯\n======================参考：https://www.jianshu.com/p/c503f7b3ed04\n羊刃重重又见禄，富贵饶金玉。 官、印相助福相资。\n\n\n华盖: 多主孤寡，总贵亦不免孤独，作僧道艺术论。\n=========================\n《理愚歌》云：华盖虽吉亦有妨，或为孽子或孤孀。填房入赘多阙口，炉钳顶笠拔缁黄。\n    又云：华盖星辰兄弟寡，天上孤高之宿也；生来若在时与胎，便是过房庶出者。\n\n\n五行缺金的建议参见 http://t.cn/E6zwOMq\n======================================\n",
  "formatted_text": "【八字排盘结果】\n\n命主：命主005\n性别：male\n出生信息：1988-01-10T08:12 - 马来西亚（西历：1988年1月10日 早上8时12分 马来西亚出生）\n\n【本地排盘输出】\n------------------------------------------------------------------------------------------------------------------------\n男命 \t公历: 1988年1月10日   农历: 1987年11月21日 穿=害 上运时间：1989-04-20 命宫:壬子 胎元:甲辰 身宫:丙午\n \t 小寒后癸水9日，辛金3日，己土18日。小寒、大寒。 小寒 1988-01-06 11:03:30 大寒 1988-01-21 04:24:17\n------------------------------------------------------------------------------------------------------------------------\n\u001b[1;36;40m丁 癸 甲 戊       伤 印 -- 才\u001b[0m      金:相 木:囚 水:死 火:休 土:旺  金2  木15  水18  火5  土20  强弱:33 中值29 强根: 有\n\u001b[1;36;40m卯 丑 子 辰       劫 财 印 才\u001b[0m     -11 湿度[-6,6] 拱：[] 解读:钉ding或v信pythontesting: 四柱：丁卯 癸丑 甲子 戊辰\n------------------------------------------------------------------------------------------------------------------------\n　　　　【年】4:1午　　　　　　　【月】-6:-4子　　　　　　　【日】3:-6　　　　　　　【时】5:-4巳|　　　\n------------------------------------------------------------------------------------------------------------------------\n\u001b[1;36;40m丁－火【伤】冲癸　　　　　　　癸－水【印】合戊冲丁　　　　　甲＋木　　　　　　　　　　　　戊＋土【才】合癸　　　　　　　\u001b[0m\n\u001b[1;36;40m卯－病长【帝】沐　　　　　　　丑－墓冠【冠】养　　　　　　　子＋绝建【沐】胎　　　　　　　辰＋衰养【衰】冠　　　　　　　\u001b[0m\n\u001b[1;36;40m乙木劫　　　　　　　　　　　　\u001b[0m\u001b[1;36;40m己土财　癸水印　辛金官　　　　\u001b[0m\u001b[1;36;40m癸水印　　　　　　　　　　　　\u001b[0m\u001b[1;36;40m戊土才　乙木劫　癸水印　　　　\u001b[0m\n\u001b[1;36;40m被刑：子　　　　　　　　　　　\u001b[0m\u001b[1;36;40m六：子　　　　　　　　　　　　\u001b[0m\u001b[1;36;40m被刑：卯　合：辰　六：丑　　　\u001b[0m\u001b[1;36;40m合：子　　　　　　　　　　　　\u001b[0m\n\u001b[1;36;40m刑：子　会：辰　害：辰　　　　\u001b[0m\u001b[1;36;40m会：子　破：辰　　　　　　　　\u001b[0m\u001b[1;36;40m刑：卯　会：丑　　　　　　　　\u001b[0m\u001b[1;36;40m会：卯　害：卯　破：丑　　　　\u001b[0m\n\u001b[1;36;40m无根　　　　　　　　　　　　　\u001b[0m\u001b[1;36;40m强：子　中：丑　弱：辰　　　　\u001b[0m\u001b[1;36;40m强：卯　中：辰　　　　　　　　\u001b[0m\u001b[1;36;40m强：丑辰　　　　　　　　　　　\u001b[0m\n↑炉中火　　　　　　　　　　　 ←桑柘木　　　　　　　　　　　 ↑海中金　　　　　　　　　　　 =大林木　　　　　　　　　　　 \n阳刃　　　　　　　　　　　　　 寡宿　天乙　　　　　　　　　　 　　　　　　　　　　　　　　 华盖　　　　　　　　　　　　 \n------------------------------------------------------------------------------------------------------------------------\n胆: 2  肝: 1  小肠: 0  心: 1  胃: 2  脾: 0  大肠: 1  肺: 0  膀胱: 0  肾: 1  三焦: 0  心包: 0  \n------------------------------------------------------------------------------------------------------------------------\n大运： 壬子 辛亥 庚戌 己酉 戊申 丁未 丙午 乙巳 甲辰 癸卯 壬寅 辛丑 \n2        壬子 沐 桑柘木    枭:壬＋合丁　　　　　子＋沐 - 癸印　　　　　　　　 会:丑  刑:卯  六:丑  被刑:卯  合:辰  神:将星\n12       辛亥 长 钗钏金    官:辛－　　　　　　空亥－长 - 壬枭　甲比　　　　　 会:子  会:丑  合:卯  神:亡神\n22       庚戌 养 钗钏金    杀:庚＋冲甲　　　　空戌＋养 - 戊才　辛官　丁伤　　 六:卯  被刑:丑  冲:辰  神:大耗 天德 月德\n32       己酉 胎 大驿土    财:己－合甲　　　　　酉－胎 - 辛官　　　　　　　　 合:丑  冲:卯  六:辰  破:子  神:桃花\n42       戊申 绝 大驿土    才:戊＋合癸　　　　　申＋绝 - 庚杀　壬枭　戊才　　 合:辰  暗:卯  合:子  神:大耗\n52       丁未 墓 天河水    伤:丁－冲癸　　　　　未－墓 - 己财　丁伤　乙劫　　 刑:丑  冲:丑  合:卯  害:子  神:天乙\n62       丙午 死 天河水    食:丙＋　　　　　　　午＋死 - 丁伤　己财　　　　　 害:丑  破:卯  冲:子  神:红艳\n72       乙巳 病 覆灯火    劫:乙－　　　　　　　巳－病 - 丙食　戊才　庚杀　　 合:丑  神:孤辰 劫煞 文昌\n82       甲辰 衰 覆灯火    比:甲＋　　　　　　　辰＋衰 - 戊才　乙劫　癸印　　 会:卯  破:丑  被刑:辰  合:子  刑:辰  害:卯  神:华盖\n------------------------------------------------------------------------------------------------------------------------\n调候： 1丁2丙庚 \t##金不换大运： 调候：喜丁 忌壬辛癸  大运：喜寅卯申酉 忌午未\n金不换大运：说明： 辰戌丑未入墓库运；巳未申酉亥月有夭折运；申酉戌亥月调候待改进！\n格局选用： 食伤生财：最佳      财格：        印格；体弱多病 杀印相生：    官杀：六亲稀少 伤官配印：\n缺四生：一生不敢作为\n月日时支没有财或偏财的禄旺。\n月日时支没有官的禄旺。\n阳刃 : 性格刚强，女命未必佳。\n华盖 : 有艺术、水准与命格相关。\n天乙 : 后天解难、女命不适合多\n寡宿 : 类似孤辰，同柱有天月德没关系。男怕孤，女怕寡。\n------------------------------------------------------------------------------------------------------------------------\n甲:比 兄弟-帝 冠 沐 衰  乙:劫 姐妹-建 衰 病 冠  丙:食 下属-沐 养 胎 冠  丁:伤 孙女-病 墓 绝 衰  戊:才 父亲-沐 养 胎 冠  \n己:财 妻-病 墓 绝 衰  庚:杀 儿子-胎 墓 死 养  辛:官 女儿-绝 养 长 墓  壬:枭 祖父-死 衰 帝 墓  癸:印 母亲-长 冠 建 养  \n\n甲[比]-5   乙[劫]-10   丙[食]-0   丁[伤]-5   戊[才]-10   己[财]-10   庚[杀]-0   辛[官]-2   壬[枭]-0   癸[印]-18   \n------------------------------------------------------------------------------------------------------------------------\n子 天贵星、志气不凡、富裕清吉。\n坐： 虽坐沐浴，若四往有禄，看印，冬生不作妻败\n甲子：调候要火。\n同一柱中，劫财、阳刃伤官都有，外表华美，富屋穷人，婚姻不稳定，富而不久；年柱不利家长，月柱不利婚姻，时柱不利子女。伤官的狂妄。基55丙申 丁酉 甲子 丁卯\n年阳刃：得不到长辈福；不知足、施恩反怨。\n基础82，成格喜官杀、身弱、忌财克印。合印留财，见利忘义.透财官杀通关或印生比劫；合冲印若无他格或调候破格。日主强凶，禄刃一支可以食伤泄。\n印月重叠：女迟婚，月阳刃者离寡，能独立谋生，有修养的才女。\n正印多的：聪明有谋略，比较含蓄，不害人，识时务。正印不怕日主死绝，反而怕太强。日主强，正印多，孤寂，不善理财。 pd41男的克妻，子嗣少。女的克母。\n男正印坐正财，夫妻不好。月柱正印坐正财专位，必离婚。在时柱，50多岁才有正常婚姻。(男) 基59 乙酉 己卯 庚子 丁亥  庚申 庚辰 庚午 己卯\n单独正印主秀气、艺术、文才。性格保守\n正印怕财。\n坐印，时偏财格：他乡发迹，改弦易宗，妻贤子孝。 母法总则：P55-1 丁丑 丁未 甲子 戊辰\n偏财明现天干，不论是否有根:财富外人可见;实际财力不及外观一半。没钱别人都不相信;协助他人常超过自己的能力\n偏财出天干，又与天月德贵人同一天干者。在年月有声明远扬的父亲，月时有聪慧的红颜知己。喜奉承。\n偏财透天干，四柱没有刑冲，长寿。女子为孝顺女，主要针对年月。时柱表示中年以后有自己的事业，善于理财。\n财格基础80:比劫用食伤通关或官杀制；身弱有比劫仍然用食伤通关。如果时柱坐实比劫，晚年破产。\n偏财透天干，讲究原则，不拘小节。喜奉承，善于享受。财格基础80\n偏财坐阳刃劫财,可做父缘薄，也可幼年家贫。也可以父先亡，要参考第一大运。偏财坐专位阳刃劫财,父亲去他乡.基61壬午 壬寅 戊子 丁巳\n月令正财，无冲刑，有贤内助，但是母亲与妻子不和。生活简朴，多为理财人士。\n伤官有才华，但是清高。要生财，或者印制。\n伤官配印，无财，有手艺，但是不善于理财。有一定个性\n伤官地支坐阳刃，力不从心 基70己酉 丁卯 甲午 辛未。背禄逐马，克官劫财。影响15年。伤官坐劫财：只适合纯粹之精明商人或严谨掌握财之人。\n局 [] 格 ['印', '才']\n\n\n《六十日用法口诀》\n=========================\n天德贵人日。坐子、沐浴，逢官临桃花。\n白玉仙子捧印来，一举成名天门开。\n贵人不向西方去，烽火空负旷世才。\n辛为正官，庚为偏官，戊己为财，见甲乙为破财，丙丁伤名利艰难，生在子月，无丑合，离祖自立，亥卯辰月主贵，巳月平常之命，午月甲死子神冲，他乡立业。申月，子嗣难有。辰月，移根换叶。亥月，文章显达。\n\n\n《穷通宝鉴》\n=========================\n\n    十二月甲木，天寒气冻，木性极寒，无生发之象，先用庚劈甲，方引丁火始得木火有通明之象，故丁次之。\n    庚丁两透，科甲恩封。庚透丁藏，小贵。丁透庚藏，小富贵。无庚者，贫贱。无丁者，寒儒。或有丁透重重，亦是富贵中人，但须比肩，能发丁之焰，自有德业才能。如无比肩，寻常之士，稍有衣食而已。或支多见水，即有比肩，亦属平常。\n    总之腊月甲木，虽有庚金，丁不可少。乏庚略可，乏丁无用。经云：甲木无根，男女夭寿  \n    \n\n\n《三命通会》\n=========================\n\n    六甲日生时戊辰,天财坐库会滋身; 富商巨贾田园盛,月带辛金名利成。 \n    甲日戊辰时,天财坐库,时上偏财,遇龙守库,主为商贾发财,田园广盛。八月带禄,财官俱有,富贵双全。忌比肩、羊刃夺财。\n    # 偏财坐印，生于夏季、有辰调候，佳命。\n    # 1-155 印库，50以后得权。\n\n    时上偏财不用多,干枝内外细搜罗; 运通财旺官生至,运拙身衰恐受磨。 \n    甲日戊辰时遇,柱中要戌相扶。财官运气展良图,喜遇钱龙守库。 \n    辛庚透干贵显,壬癸滋助不枯。只怕比劫弟兄多,岁运逢之有祸。\n\n    甲子日戊辰时,主移根换叶,改姓易宗,妻贤子孝,作高 命论。未月,行北方运,贵。酉月,北方运,大贵。 \n\n    甲寅日戊辰时,龙吟虎啸格,贵。纯辰,中贵。纯寅康寿。 亥卯未三合,财旺身强,大贵。酉丑申年月亦吉。 \n\n    甲辰日戊辰时,刑冲发财,妻重子晚,双亲有克。酉月三四品贵。丑月亦贵。地支纯辰,大贵。\n\n    甲午日戊辰时,财多成败,早岁灰心。亥子丑卯午未年月大贵。酉月亦贵。\n\n    甲申日戊辰时,主孤,僧道清高。丑月富贵。寅月尤贵。 \n    甲戌日戊辰时,大富,年月扶合亦贵。寅亥年月,三四品贵。但时日并冲克,早年身孤,中年发福。\n    \n\n\n《十二时辰（初中末）出生吉凶》\n=========================\n辰时初\n衣禄自然来，兄弟六亲林，父母难刑克，晚景更无忧。\n辰时初父母在，为人性急，六亲有力，长子难招，兄弟不和，心慈善，宜手艺营生，初限平平，四十二岁后渐好。\n\n辰时中\n衣禄得人抬，先忧后吉来，六亲虽冷淡，末限足钱财。\n辰时中先克父，为人心行公道，性急直燥，出入有贵人扶持，离祖成家，六亲兄弟情疏，初年不济，末限胜前。\n\n辰时末\n衣禄自然有，朱紫作朝郎，一朝命发达，富贵有名声。\n辰时末先克母，为人聪明，衣禄丰盈，大有声名，六亲大旺，兄分有顾盼，为官头目之称，女命益夫，旺子福禄双全。\n\n\n大运\n========================================================================================================================\n2        壬子 沐 桑柘木    枭:壬＋合丁　　　　　子＋沐 - 癸印　　　　　　　　 会:丑  刑:卯  六:丑  被刑:卯  合:辰  神:将星\n  2 1989 己巳 病 大林木    财:己－合甲　　　　　巳－病 - 丙食　戊才　庚杀　　 合:丑  神:孤辰 劫煞 文昌\n  3 1990 庚午 死 路旁土    杀:庚＋冲甲　　　　　午＋死 - 丁伤　己财　　　　　 害:丑  冲:子  神:天德 月德 红艳\n  4 1991 辛未 墓 路旁土    官:辛－　　　　　　　未－墓 - 己财　丁伤　乙劫　　 刑:丑  冲:丑  合:卯  害:子  神:天乙\n  5 1992 壬申 绝 剑锋金    枭:壬＋合丁　　　　　申＋绝 - 庚杀　壬枭　戊才　　 合:辰  暗:卯  合:子  神:大耗\n  6 1993 癸酉 胎 剑锋金    印:癸－合戊冲丁　　　酉－胎 - 辛官　　　　　　　　 合:丑  冲:卯  六:辰  神:桃花\n  7 1994 甲戌 养 山头火    比:甲＋　　　　　　空戌＋养 - 戊才　辛官　丁伤　　 六:卯  被刑:丑  冲:辰  --夹：戌  神:大耗\n  8 1995 乙亥 长 山头火    劫:乙－　　　　　　空亥－长 - 壬枭　甲比　　　　　 会:子  会:丑  合:卯  神:亡神\n  9 1996 丙子 沐 涧下水    食:丙＋冲壬　　　　　子＋沐 - 癸印　　　　　　　　 会:丑  刑:卯  六:丑  被刑:卯  合:辰  神:将星\n 10 1997 丁丑 冠 涧下水    伤:丁－合壬冲癸　　　丑－冠 - 己财　癸印　辛官　　 会:子  六:子  --夹：寅  神:寡宿 天乙\n 11 1998 戊寅 建 城头土    才:戊＋合癸　　　　　寅＋建 - 甲比　丙食　戊才　　 会:卯  会:辰  暗:丑  --夹：卯  神:驿马\n12       辛亥 长 钗钏金    官:辛－　　　　　　空亥－长 - 壬枭　甲比　　　　　 会:子  会:丑  合:卯  神:亡神\n 12 1999 己卯 帝 城头土    财:己－合甲　　　　　卯－帝 - 乙劫　　　　　　　　 合:亥  害:辰  被刑:子  刑:子  会:辰  神:阳刃\n 13 2000 庚辰 衰 白蜡金    杀:庚＋冲甲　　　　　辰＋衰 - 戊才　乙劫　癸印　　 会:卯  被刑:辰  合:子  刑:辰  害:卯  神:天德 月德 华盖\n 14 2001 辛巳 病 白蜡金    官:辛－　　　　　　　巳－病 - 丙食　戊才　庚杀　　 冲:亥  合:丑  神:孤辰 劫煞 文昌\n 15 2002 壬午 死 杨柳木    枭:壬＋合丁　　　　　午＋死 - 丁伤　己财　　　　　 害:丑  暗:亥  冲:子  神:红艳\n 16 2003 癸未 墓 杨柳木    印:癸－合戊冲丁　　　未－墓 - 己财　丁伤　乙劫　　 刑:丑  合:卯  害:子  合:亥  冲:丑  神:天乙\n 17 2004 甲申 绝 井泉水    比:甲＋　　　　　　　申＋绝 - 庚杀　壬枭　戊才　　 害:亥  合:辰  暗:卯  合:子  神:大耗\n 18 2005 乙酉 胎 井泉水    劫:乙－冲辛　　　　　酉－胎 - 辛官　　　　　　　　 合:丑  冲:卯  六:辰  神:桃花\n 19 2006 丙戌 养 屋上土    食:丙＋合辛　　　　空戌＋养 - 戊才　辛官　丁伤　　 六:卯  被刑:丑  冲:辰  神:大耗\n 20 2007 丁亥 长 屋上土    伤:丁－冲癸　　　　空亥－长 - 壬枭　甲比　　　　　 会:子  会:丑  刑:亥  合:卯  被刑:亥  神:亡神\n 21 2008 戊子 沐 霹雳火    才:戊＋合癸　　　　　子＋沐 - 癸印　　　　　　　　 会:丑  会:亥  刑:卯  六:丑  被刑:卯  合:辰  神:将星\n22       庚戌 养 钗钏金    杀:庚＋冲甲　　　　空戌＋养 - 戊才　辛官　丁伤　　 六:卯  被刑:丑  冲:辰  神:大耗 天德 月德\n 22 2009 己丑 冠 霹雳火    财:己－合甲　　　　　丑－冠 - 己财　癸印　辛官　　 会:子  刑:戌  六:子  神:寡宿 天乙\n 23 2010 庚寅 建 松柏木    杀:庚＋冲甲　　　　　寅＋建 - 甲比　丙食　戊才　　 会:卯  合:戌  会:辰  暗:丑  --拱：午  神:天德 月德 驿马\n 24 2011 辛卯 帝 松柏木    官:辛－　　　　　　　卯－帝 - 乙劫　　　　　　　　 六:戌  害:辰  被刑:子  刑:子  会:辰  神:阳刃\n 25 2012 壬辰 衰 长流水    枭:壬＋合丁　　　　　辰＋衰 - 戊才　乙劫　癸印　　 会:卯  冲:戌  被刑:辰  合:子  刑:辰  害:卯  神:华盖\n 26 2013 癸巳 病 长流水    印:癸－合戊冲丁　　　巳－病 - 丙食　戊才　庚杀　　 合:丑  --拱：酉  神:孤辰 劫煞 文昌\n 27 2014 甲午 死 砂中金    比:甲＋冲庚　　　　　午＋死 - 丁伤　己财　　　　　 合:戌  害:丑  冲:子  神:红艳\n 28 2015 乙未 墓 砂中金    劫:乙－合庚　　　　　未－墓 - 己财　丁伤　乙劫　　 刑:丑  合:卯  害:子  冲:丑  被刑:戌  神:天乙  四库：辰戌丑未\n 29 2016 丙申 绝 山下火    食:丙＋　　　　　　　申＋绝 - 庚杀　壬枭　戊才　　 会:戌  合:辰  暗:卯  合:子  神:大耗\n 30 2017 丁酉 胎 山下火    伤:丁－冲癸　　　　　酉－胎 - 辛官　　　　　　　　 六:辰  冲:卯  合:丑  害:戌  会:戌  神:桃花\n 31 2018 戊戌 养 平地木    才:戊＋合癸　　　　空戌＋养 - 戊才　辛官　丁伤　　 六:卯  被刑:丑  冲:辰  神:大耗\n32       己酉 胎 大驿土    财:己－合甲　　　　　酉－胎 - 辛官　　　　　　　　 合:丑  冲:卯  六:辰  破:子  神:桃花\n 32 2019 己亥 长 平地木    财:己－合甲　　　　空亥－长 - 壬枭　甲比　　　　　 会:子  会:丑  合:卯  --夹：戌  神:亡神\n 33 2020 庚子 沐 壁上土    杀:庚＋冲甲　　　　　子＋沐 - 癸印　　　　　　　　 会:丑  刑:卯  六:丑  被刑:卯  合:辰  神:天德 月德 将星\n 34 2021 辛丑 冠 壁上土    官:辛－　　　　　　　丑－冠 - 己财　癸印　辛官　　 会:子  六:子  合:酉  神:寡宿 天乙\n 35 2022 壬寅 建 金泊金    枭:壬＋合丁　　　　　寅＋建 - 甲比　丙食　戊才　　 会:卯  会:辰  暗:丑  神:驿马\n 36 2023 癸卯 帝 金泊金    印:癸－合戊冲丁　　　卯－帝 - 乙劫　　　　　　　　 冲:酉  害:辰  被刑:子  刑:子  会:辰  --夹：寅  神:阳刃\n 37 2024 甲辰 衰 覆灯火    比:甲＋合己　　　　　辰＋衰 - 戊才　乙劫　癸印　　 会:卯  六:酉  被刑:辰  合:子  刑:辰  害:卯  神:华盖\n 38 2025 乙巳 病 覆灯火    劫:乙－　　　　　　　巳－病 - 丙食　戊才　庚杀　　 合:酉  合:丑  神:孤辰 劫煞 文昌\n 39 2026 丙午 死 天河水    食:丙＋　　　　　　　午＋死 - 丁伤　己财　　　　　 害:丑  冲:子  神:红艳  四败：子午卯酉\n 40 2027 丁未 墓 天河水    伤:丁－冲癸　　　　　未－墓 - 己财　丁伤　乙劫　　 刑:丑  冲:丑  合:卯  害:子  神:天乙\n 41 2028 戊申 绝 大驿土    才:戊＋合癸　　　　　申＋绝 - 庚杀　壬枭　戊才　　 会:酉  合:辰  暗:卯  合:子  神:大耗\n42       戊申 绝 大驿土    才:戊＋合癸　　　　　申＋绝 - 庚杀　壬枭　戊才　　 合:辰  暗:卯  合:子  神:大耗\n 42 2029 己酉 胎 大驿土    财:己－合甲　　　　　酉－胎 - 辛官　　　　　　　　 合:丑  冲:卯  六:辰  会:申  神:桃花\n 43 2030 庚戌 养 钗钏金    杀:庚＋冲甲　　　　空戌＋养 - 戊才　辛官　丁伤　　 六:卯  被刑:丑  冲:辰  会:申  神:大耗 天德 月德\n 44 2031 辛亥 长 钗钏金    官:辛－　　　　　　空亥－长 - 壬枭　甲比　　　　　 会:子  会:丑  合:卯  害:申  神:亡神\n 45 2032 壬子 沐 桑柘木    枭:壬＋合丁　　　　　子＋沐 - 癸印　　　　　　　　 会:丑  刑:卯  六:丑  被刑:卯  合:辰  合:申  神:将星\n 46 2033 癸丑 冠 桑柘木 *  印:癸－合戊冲丁　　　丑－冠 - 己财　癸印　辛官　　 会:子  六:子  神:寡宿 天乙\n 47 2034 甲寅 建 大溪水    比:甲＋　　　　　　　寅＋建 - 甲比　丙食　戊才　　 会:卯  被刑:申  冲:申  暗:丑  会:辰  --夹：丑  神:驿马\n 48 2035 乙卯 帝 大溪水    劫:乙－　　　　　　　卯－帝 - 乙劫　　　　　　　　 害:辰  被刑:子  刑:子  会:辰  暗:申  神:阳刃\n 49 2036 丙辰 衰 砂中土    食:丙＋　　　　　　　辰＋衰 - 戊才　乙劫　癸印　　 会:卯  被刑:辰  合:子  刑:辰  合:申  害:卯  神:华盖\n 50 2037 丁巳 病 砂中土    伤:丁－冲癸　　　　　巳－病 - 丙食　戊才　庚杀　　 合:丑  刑:申  六:申  --夹：辰  神:孤辰 劫煞 文昌\n 51 2038 戊午 死 天上火    才:戊＋合癸　　　　　午＋死 - 丁伤　己财　　　　　 害:丑  冲:子  --夹：巳  --夹：未  神:红艳\n52       丁未 墓 天河水    伤:丁－冲癸　　　　　未－墓 - 己财　丁伤　乙劫　　 刑:丑  冲:丑  合:卯  害:子  神:天乙\n 52 2039 己未 墓 天上火    财:己－合甲　　　　　未－墓 - 己财　丁伤　乙劫　　 刑:丑  冲:丑  合:卯  害:子  神:天乙\n 53 2040 庚申 绝 石榴木    杀:庚＋冲甲　　　　　申＋绝 - 庚杀　壬枭　戊才　　 合:辰  暗:卯  合:子  神:大耗 天德 月德\n 54 2041 辛酉 胎 石榴木    官:辛－　　　　　　　酉－胎 - 辛官　　　　　　　　 合:丑  冲:卯  六:辰  神:桃花\n 55 2042 壬戌 养 大海水    枭:壬＋合丁　　　　空戌＋养 - 戊才　辛官　丁伤　　 六:卯  被刑:丑  刑:未  冲:辰  神:大耗  四库：辰戌丑未\n 56 2043 癸亥 长 大海水    印:癸－合戊冲丁　　空亥－长 - 壬枭　甲比　　　　　 会:子  合:未  会:丑  合:卯  --夹：子  神:亡神\n 57 2044 甲子 沐 海中金 *  比:甲＋　　　　　　　子＋沐 - 癸印　　　　　　　　 会:丑  害:未  刑:卯  六:丑  被刑:卯  合:辰  神:将星\n 58 2045 乙丑 冠 海中金    劫:乙－　　　　　　　丑－冠 - 己财　癸印　辛官　　 会:子  六:子  被刑:未  冲:未  神:寡宿 天乙\n 59 2046 丙寅 建 炉中火    食:丙＋　　　　　　　寅＋建 - 甲比　丙食　戊才　　 会:卯  会:辰  暗:丑  神:驿马\n 60 2047 丁卯 帝 炉中火 *  伤:丁－冲癸　　　　　卯－帝 - 乙劫　　　　　　　　 害:辰  合:未  被刑:子  刑:子  会:辰  神:阳刃\n 61 2048 戊辰 衰 大林木 *  才:戊＋合癸　　　　　辰＋衰 - 戊才　乙劫　癸印　　 会:卯  被刑:辰  合:子  刑:辰  害:卯  神:华盖\n62       丙午 死 天河水    食:丙＋　　　　　　　午＋死 - 丁伤　己财　　　　　 害:丑  破:卯  冲:子  神:红艳\n 62 2049 己巳 病 大林木    财:己－合甲　　　　　巳－病 - 丙食　戊才　庚杀　　 合:丑  会:午  神:孤辰 劫煞 文昌\n 63 2050 庚午 死 路旁土    杀:庚＋冲甲　　　　　午＋死 - 丁伤　己财　　　　　 被刑:午  害:丑  刑:午  冲:子  神:天德 月德 红艳\n 64 2051 辛未 墓 路旁土    官:辛－合丙　　　　　未－墓 - 己财　丁伤　乙劫　　 刑:丑  合:卯  害:子  冲:丑  六:午  会:午  神:天乙\n 65 2052 壬申 绝 剑锋金    枭:壬＋合丁冲丙　　　申＋绝 - 庚杀　壬枭　戊才　　 合:辰  暗:卯  合:子  神:大耗\n 66 2053 癸酉 胎 剑锋金    印:癸－合戊冲丁　　　酉－胎 - 辛官　　　　　　　　 合:丑  冲:卯  六:辰  神:桃花  四败：子午卯酉\n 67 2054 甲戌 养 山头火    比:甲＋　　　　　　空戌＋养 - 戊才　辛官　丁伤　　 六:卯  被刑:丑  冲:辰  合:午  --夹：戌  神:大耗\n 68 2055 乙亥 长 山头火    劫:乙－　　　　　　空亥－长 - 壬枭　甲比　　　　　 会:子  会:丑  合:卯  暗:午  神:亡神\n 69 2056 丙子 沐 涧下水    食:丙＋　　　　　　　子＋沐 - 癸印　　　　　　　　 会:丑  刑:卯  六:丑  被刑:卯  合:辰  冲:午  神:将星\n 70 2057 丁丑 冠 涧下水    伤:丁－冲癸　　　　　丑－冠 - 己财　癸印　辛官　　 会:子  六:子  害:午  --夹：寅  神:寡宿 天乙\n 71 2058 戊寅 建 城头土    才:戊＋合癸　　　　　寅＋建 - 甲比　丙食　戊才　　 会:卯  合:午  会:辰  暗:丑  --夹：卯  神:驿马\n72       乙巳 病 覆灯火    劫:乙－　　　　　　　巳－病 - 丙食　戊才　庚杀　　 合:丑  神:孤辰 劫煞 文昌\n 72 2059 己卯 帝 城头土    财:己－合甲　　　　　卯－帝 - 乙劫　　　　　　　　 被刑:子  刑:子  会:辰  害:辰  神:阳刃\n 73 2060 庚辰 衰 白蜡金    杀:庚＋合乙冲甲　　　辰＋衰 - 戊才　乙劫　癸印　　 会:卯  被刑:辰  合:子  刑:辰  害:卯  神:天德 月德 华盖\n 74 2061 辛巳 病 白蜡金    官:辛－冲乙　　　　　巳－病 - 丙食　戊才　庚杀　　 合:丑  神:孤辰 劫煞 文昌\n 75 2062 壬午 死 杨柳木    枭:壬＋合丁　　　　　午＋死 - 丁伤　己财　　　　　 害:丑  会:巳  冲:子  神:红艳\n 76 2063 癸未 墓 杨柳木    印:癸－合戊冲丁　　　未－墓 - 己财　丁伤　乙劫　　 会:巳  刑:丑  合:卯  害:子  冲:丑  神:天乙\n 77 2064 甲申 绝 井泉水    比:甲＋　　　　　　　申＋绝 - 庚杀　壬枭　戊才　　 暗:卯  六:巳  合:辰  合:子  被刑:巳  神:大耗\n 78 2065 乙酉 胎 井泉水    劫:乙－　　　　　　　酉－胎 - 辛官　　　　　　　　 合:巳  合:丑  冲:卯  六:辰  神:桃花\n 79 2066 丙戌 养 屋上土    食:丙＋　　　　　　空戌＋养 - 戊才　辛官　丁伤　　 六:卯  被刑:丑  冲:辰  神:大耗\n 80 2067 丁亥 长 屋上土    伤:丁－冲癸　　　　空亥－长 - 壬枭　甲比　　　　　 会:子  会:丑  冲:巳  合:卯  神:亡神\n 81 2068 戊子 沐 霹雳火    才:戊＋合癸　　　　　子＋沐 - 癸印　　　　　　　　 会:丑  刑:卯  六:丑  被刑:卯  合:辰  神:将星\n82       甲辰 衰 覆灯火    比:甲＋　　　　　　　辰＋衰 - 戊才　乙劫　癸印　　 会:卯  破:丑  被刑:辰  合:子  刑:辰  害:卯  神:华盖\n 82 2069 己丑 冠 霹雳火    财:己－合甲　　　　　丑－冠 - 己财　癸印　辛官　　 会:子  六:子  神:寡宿 天乙\n 83 2070 庚寅 建 松柏木    杀:庚＋冲甲　　　　　寅＋建 - 甲比　丙食　戊才　　 会:卯  会:辰  暗:丑  神:天德 月德 驿马\n 84 2071 辛卯 帝 松柏木    官:辛－　　　　　　　卯－帝 - 乙劫　　　　　　　　 被刑:子  刑:子  会:辰  害:辰  神:阳刃\n 85 2072 壬辰 衰 长流水    枭:壬＋合丁　　　　　辰＋衰 - 戊才　乙劫　癸印　　 会:卯  被刑:辰  合:子  刑:辰  害:卯  神:华盖\n 86 2073 癸巳 病 长流水    印:癸－合戊冲丁　　　巳－病 - 丙食　戊才　庚杀　　 合:丑  --拱：酉  神:孤辰 劫煞 文昌\n 87 2074 甲午 死 砂中金    比:甲＋　　　　　　　午＋死 - 丁伤　己财　　　　　 害:丑  冲:子  --夹：巳  神:红艳\n 88 2075 乙未 墓 砂中金    劫:乙－　　　　　　　未－墓 - 己财　丁伤　乙劫　　 刑:丑  冲:丑  合:卯  害:子  神:天乙\n 89 2076 丙申 绝 山下火    食:丙＋　　　　　　　申＋绝 - 庚杀　壬枭　戊才　　 合:辰  暗:卯  合:子  神:大耗\n 90 2077 丁酉 胎 山下火    伤:丁－冲癸　　　　　酉－胎 - 辛官　　　　　　　　 合:丑  冲:卯  六:辰  神:桃花\n 91 2078 戊戌 养 平地木    才:戊＋合癸　　　　空戌＋养 - 戊才　辛官　丁伤　　 六:卯  被刑:丑  冲:辰  神:大耗\n星宿 虚 虚星造作主灾殃，男女孤眠不一双，内乱风声无礼节，儿孙媳妇伴人床，开门放水遭灾祸，虎咬蛇伤又卒亡，三三五五连年病，家破人亡不可当。\n('闭', '闭藏的日子 宜：安门、伐木、修造、动土。 忌：出行、嫁娶。')\n========================================================================================================================\n| 玉堂贵人： 丑 \n\n------------------------------------------------------------------------------------------------------------------------\n出身: 一般\n财少身强，柱有比劫，不为福\n\n印分析 **** 喜:食神 天月德 七煞 逢印看煞 以官为引   忌： 刑冲 伤官 死墓 辰戊印怕木 丑未印不怕木\n一曰正印 二曰魁星 三曰孙极星\n以印绶多者为上,月最要,日时次之,年干虽重,须归禄月、日、时,方可取用,若年露印,月日时无,亦不济事。\n======================================\n伤食：身强印旺，恐其太过，泄身以为秀气；若印浅身轻，而用层层伤食，则寒贫之局矣。\n有印多而用财者，印重身强，透财以抑太过，权而用之，只要根深，无防财破。 若印轻财重，又无劫财以救，则为贪财破印，贫贱之局也。\n印绶复遇拱禄、专禄、归禄、鼠贵、夹贵、时贵等格,尤为奇特,但主少子或无子,印绶多者清孤。\n化印为劫；弃之以就财官\n\n------------------------------------------------------------------------------------------------------------------------\n========================================================================================================================\n你属: 甲 特点：-- 雷龙 梁栋 禄寅;斧斤斫削成其器。木不南奔;喜春运不喜西方,春生,处世安然,必寿。 \n\n年份: 卯 特点：-- 琼林 乙木 正东 仲春 卯年遇巳未时者，是为兔入月宫之象，主大贵。 \n\n\n羊刃: 甲 卯\n======================参考：https://www.jianshu.com/p/c503f7b3ed04\n羊刃重重又见禄，富贵饶金玉。 官、印相助福相资。\n\n\n华盖: 多主孤寡，总贵亦不免孤独，作僧道艺术论。\n=========================\n《理愚歌》云：华盖虽吉亦有妨，或为孽子或孤孀。填房入赘多阙口，炉钳顶笠拔缁黄。\n    又云：华盖星辰兄弟寡，天上孤高之宿也；生来若在时与胎，便是过房庶出者。\n\n\n五行缺金的建议参见 http://t.cn/E6zwOMq\n======================================\n"
}